mimocorb2/__init__.py
mimocorb2/__main__.py
mimocorb2/control.py
mimocorb2/helpers.py
mimocorb2/mimo_buffer.py
mimocorb2/mimo_worker.py
mimocorb2/worker_templates.py
mimocorb2/control_interfaces/__init__.py
mimocorb2/control_interfaces/control_gui.py
mimocorb2/control_interfaces/control_stats_logger.py
mimocorb2/control_interfaces/control_terminal.py
mimocorb2/control_interfaces/gui.ui
mimocorb2/functions/__init__.py
mimocorb2/functions/analyzers.py
mimocorb2/functions/data.py
mimocorb2/functions/doc_template.py
mimocorb2/functions/exporters.py
mimocorb2/functions/misc.py
mimocorb2/functions/observers.py
mimocorb2/functions/visualizers.py
mimocorb2/functions/importers/__init__.py
mimocorb2/functions/importers/picoscope.py
mimocorb2/functions/importers/redpitaya.py
mimocorb2-0.0.3.dist-info/licenses/LICENSE
mimocorb2-0.0.3.dist-info/METADATA
mimocorb2-0.0.3.dist-info/WHEEL
mimocorb2-0.0.3.dist-info/entry_points.txt
mimocorb2-0.0.3.dist-info/top_level.txt
mimocorb2-0.0.3.dist-info/RECORD
