Metadata-Version: 2.4
Name: mimoCoRB2
Version: 0.0.3
Summary: Multiple In Multiple Out Configurable Ring Buffer manager
Author-email: Julian Baader <julian.baader@gmx.de>
License: MIT License
Requires-Python: >=3.12
License-File: LICENSE
Requires-Dist: numpy
Requires-Dist: pyyaml
Requires-Dist: graphviz
Requires-Dist: scipy
Requires-Dist: pandas
Requires-Dist: matplotlib
Requires-Dist: PyQt5
Requires-Dist: psutil
Provides-Extra: dev
Requires-Dist: sphinx; extra == "dev"
Requires-Dist: sphinx-autodoc-typehints; extra == "dev"
Requires-Dist: ruff; extra == "dev"
Requires-Dist: pre-commit; extra == "dev"
Requires-Dist: sphinxcontrib-tikz; extra == "dev"
Dynamic: license-file
